[
    {
        "key": "alt+oem_comma",
        "command": "workbench.action.showCommands"
    },
    {
        "key": "alt+oem_period",
        "command": "workbench.action.findInFiles",
        "when": "!searchInputBoxFocus"
    },
    {
        "key": "alt+p",
        "command": "workbench.action.quickOpen"
    },
    {
        "key": "alt+e",
        "command": "workbench.view.explorer"
    },
    {
        "key": "alt+u",
        "command": "workbench.action.terminal.toggleTerminal"
    },
    {
        "key": "alt+a",
        "command": "workbench.action.toggleActivityBarVisibility"
    },
    {
        "key": "alt+b",
        "command": "workbench.action.toggleSidebarVisibility"
    },
    {
        "key": "ctrl+b",
        "command": "-workbench.action.toggleSidebarVisibility"
    },
    {
        "key": "alt+m",
        "command": "workbench.action.toggleMenuBar"
    }
]
